Metadata-Version: 2.1
Name: findtable
Version: 0.1
Summary: get cleaner tables from urls
Home-page: UNKNOWN
Author: SayaGugu
Author-email: 2708475759@qq.com
License: apache 3.0
Platform: UNKNOWN
Requires: os
Requires: pandas
Requires: requests
Requires: opencc
Requires: openpyxl
